{
 "apps": [
  {
   "id": "adhd-test",
   "type": "test",
   "title": "ADHD 傾向測驗",
   "author": "MIMI FACTORY",
   "date": "2026-07-24",
   "color1": "#7aa6ff",
   "color2": "#b78bf5",
   "teaser": "apps/adhd-test.html",
   "premium": "apps/adhd-test.html",
   "desc": "分心不是懶惰 — 溫柔地檢視你現在的專注力狀態"
  },
  {
   "id": "ai-new-human",
   "type": "test",
   "title": "AI 新人類測驗",
   "author": "MIMI FACTORY",
   "date": "2026-07-24",
   "color1": "#7aa6ff",
   "color2": "#b78bf5",
   "teaser": "apps/ai-new-human.html",
   "premium": "apps/ai-new-human.html",
   "desc": "AI 吞噬工作的時代，8 種人活下來。你是哪種生存角色？"
  },
  {
   "id": "eq-emotional-intelligence-test",
   "type": "test",
   "title": "EQ 情緒智能測驗",
   "author": "MIMI FACTORY",
   "date": "2026-07-24",
   "color1": "#7aa6ff",
   "color2": "#b78bf5",
   "teaser": "apps/eq-emotional-intelligence-test.html",
   "premium": "apps/eq-emotional-intelligence-test.html",
   "desc": "自我覺察、調節、同理、表達 — 用 16 題畫出你的 4 種情緒技能"
  },
  {
   "id": "iq-brain-test",
   "type": "test",
   "title": "IQ 頭腦測驗",
   "author": "MIMI FACTORY",
   "date": "2026-07-24",
   "color1": "#7aa6ff",
   "color2": "#b78bf5",
   "teaser": "apps/iq-brain-test.html",
   "premium": "apps/iq-brain-test.html",
   "desc": "數列·邏輯·圖形·語文 15 題 — 還分析你頭腦最強的領域"
  },
  {
   "id": "mbti-test",
   "type": "test",
   "title": "MBTI測驗",
   "author": "MIMI FACTORY",
   "date": "2026-07-24",
   "color1": "#7aa6ff",
   "color2": "#b78bf5",
   "teaser": "apps/mbti-test.html",
   "premium": "apps/mbti-test.html",
   "desc": "每點一下代碼就跳動 — 最後解鎖唯一屬於你的類型"
  },
  {
   "id": "mbti-match",
   "type": "test",
   "title": "兩人MBTI配對",
   "author": "MIMI FACTORY",
   "date": "2026-07-24",
   "color1": "#7aa6ff",
   "color2": "#b78bf5",
   "teaser": "apps/mbti-match.html",
   "premium": "apps/mbti-match.html",
   "desc": "一支手機輪流測 — 算出配對指數和拉近距離的任務"
  },
  {
   "id": "sq-social-intelligence",
   "type": "test",
   "title": "SQ 社會智能測驗",
   "author": "MIMI FACTORY",
   "date": "2026-07-24",
   "color1": "#7aa6ff",
   "color2": "#b78bf5",
   "teaser": "apps/sq-social-intelligence.html",
   "premium": "apps/sq-social-intelligence.html",
   "desc": "不是讀書的腦，是關係的腦 — 16 題診斷你的關係技術"
  },
  {
   "id": "tarot",
   "type": "test",
   "title": "塔羅心理卡",
   "author": "MIMI FACTORY",
   "date": "2026-07-11",
   "color1": "#f4c66f",
   "color2": "#93a8ff",
   "teaser": "apps/tarot.html",
   "premium": "apps/tarot.html",
   "desc": "抽的不是命運，是問題 — 22張象徵變成心理學的鏡子"
  },
  {
   "id": "gwangjang",
   "type": "test",
   "title": "《廣場》多巴胺大師測驗",
   "author": "MIMI FACTORY",
   "date": "2026-07-24",
   "color1": "#7aa6ff",
   "color2": "#b78bf5",
   "teaser": "apps/gwangjang.html",
   "premium": "apps/gwangjang.html",
   "desc": "用多巴胺反覆掌握分斷文學經典《廣場》核心的大師測驗。"
  },
  {
   "id": "cut-them-off",
   "type": "test",
   "title": "那個人，該斷捨離嗎？",
   "author": "MIMI FACTORY",
   "date": "2026-07-24",
   "color1": "#7aa6ff",
   "color2": "#b78bf5",
   "teaser": "apps/cut-them-off.html",
   "premium": "apps/cut-them-off.html",
   "desc": "用 15 個行為，替心裡那個人亮起關係紅綠燈。"
  },
  {
   "id": "go-giver",
   "type": "test",
   "title": "給予者大師測驗",
   "author": "MIMI FACTORY",
   "date": "2026-07-24",
   "color1": "#7aa6ff",
   "color2": "#b78bf5",
   "teaser": "apps/go-giver.html",
   "premium": "apps/go-giver.html",
   "desc": "給予的人才會成功 — 用測驗掌握給予者的五大法則"
  },
  {
   "id": "give-and-take",
   "type": "test",
   "title": "《給予》大師測驗",
   "author": "MIMI FACTORY",
   "date": "2026-07-24",
   "color1": "#7aa6ff",
   "color2": "#b78bf5",
   "teaser": "apps/give-and-take.html",
   "premium": "apps/give-and-take.html",
   "desc": "給予的人真的只會吃虧嗎？用測驗一次搞懂給予者、索取者、互利者的祕密。"
  },
  {
   "id": "dealbreaker-button",
   "type": "test",
   "title": "我的地雷按鈕",
   "author": "MIMI FACTORY",
   "date": "2026-07-24",
   "color1": "#7aa6ff",
   "color2": "#b78bf5",
   "teaser": "apps/dealbreaker-button.html",
   "premium": "apps/dealbreaker-button.html",
   "desc": "你把一個人切得多容易？測量你的地雷按鈕靈敏度。"
  },
  {
   "id": "attachment-style",
   "type": "test",
   "title": "我的依附類型",
   "author": "MIMI FACTORY",
   "date": "2026-07-24",
   "color1": "#7aa6ff",
   "color2": "#b78bf5",
   "teaser": "apps/attachment-style.html",
   "premium": "apps/attachment-style.html",
   "desc": "越靠近越會冒出來的我 — 4 種依附類型測驗"
  },
  {
   "id": "recovery-speed",
   "type": "test",
   "title": "回復速度測驗",
   "author": "MIMI FACTORY",
   "date": "2026-07-24",
   "color1": "#7aa6ff",
   "color2": "#b78bf5",
   "teaser": "apps/recovery-speed.html",
   "premium": "apps/recovery-speed.html",
   "desc": "崩潰隔天，你會怎麼重新站起來？12 題測出回復速度 4 種類型"
  },
  {
   "id": "emotion-resolution",
   "type": "test",
   "title": "情緒解析度測驗",
   "author": "MIMI FACTORY",
   "date": "2026-07-24",
   "color1": "#7aa6ff",
   "color2": "#b78bf5",
   "teaser": "apps/emotion-resolution.html",
   "premium": "apps/emotion-resolution.html",
   "desc": "用12個場景測量，你的情緒是幾個像素？"
  },
  {
   "id": "do-you-know-me",
   "type": "test",
   "title": "你，懂我嗎？",
   "author": "MIMI FACTORY",
   "date": "2026-07-24",
   "color1": "#7aa6ff",
   "color2": "#b78bf5",
   "teaser": "apps/do-you-know-me.html",
   "premium": "apps/do-you-know-me.html",
   "desc": "關於我的 10 道題，對方能猜對幾題？猜錯就從那裡開始聊。"
  },
  {
   "id": "analects",
   "type": "test",
   "title": "論語大師測驗",
   "author": "MIMI FACTORY",
   "date": "2026-07-24",
   "color1": "#7aa6ff",
   "color2": "#b78bf5",
   "teaser": "apps/analects.html",
   "premium": "apps/analects.html",
   "desc": "用多巴胺反覆測驗，熟記孔子《論語》的核心"
  },
  {
   "id": "multiple-intelligences",
   "type": "test",
   "title": "多元智能測驗",
   "author": "MIMI FACTORY",
   "date": "2026-07-24",
   "color1": "#7aa6ff",
   "color2": "#b78bf5",
   "teaser": "apps/multiple-intelligences.html",
   "premium": "apps/multiple-intelligences.html",
   "desc": "光靠 IQ 說明不了你 — 用加德納的 8 種智能畫出你的地圖。"
  },
  {
   "id": "demian",
   "type": "test",
   "title": "德米安大師測驗",
   "author": "MIMI FACTORY",
   "date": "2026-07-24",
   "color1": "#7aa6ff",
   "color2": "#b78bf5",
   "teaser": "apps/demian.html",
   "premium": "apps/demian.html",
   "desc": "用多巴胺反覆測驗，記住赫塞《德米安》的核心。"
  },
  {
   "id": "self-study",
   "type": "test",
   "title": "自學力 大師測驗",
   "author": "MIMI FACTORY",
   "date": "2026-07-24",
   "color1": "#7aa6ff",
   "color2": "#b78bf5",
   "teaser": "apps/self-study.html",
   "premium": "apps/self-study.html",
   "desc": "透過測驗，精通 AI 時代你唯一需要的那股力量 — 自學力"
  },
  {
   "id": "36-questions",
   "type": "test",
   "title": "打開心房的36個問題",
   "author": "MIMI FACTORY",
   "date": "2026-07-24",
   "color1": "#7aa6ff",
   "color2": "#b78bf5",
   "teaser": "apps/36-questions.html",
   "premium": "apps/36-questions.html",
   "desc": "心理學驗證過的對話 — 越問越深的36個問題，最後是4分鐘的凝視。"
  },
  {
   "id": "mujin",
   "type": "test",
   "title": "《霧津紀行》多巴胺大師測驗",
   "author": "MIMI FACTORY",
   "date": "2026-07-24",
   "color1": "#7aa6ff",
   "color2": "#b78bf5",
   "teaser": "apps/mujin.html",
   "premium": "apps/mujin.html",
   "desc": "用多巴胺反覆掌握金承鈺經典短篇《霧津紀行》核心的大師測驗。"
  },
  {
   "id": "collapse",
   "type": "test",
   "title": "大崩壞 精通測驗",
   "author": "MIMI FACTORY",
   "date": "2026-07-24",
   "color1": "#7aa6ff",
   "color2": "#b78bf5",
   "teaser": "apps/collapse.html",
   "premium": "apps/collapse.html",
   "desc": "文明為何崩塌、又如何倖存 — 30 題掌握核心的反覆測驗"
  },
  {
   "id": "balance-couple-chemistry",
   "type": "test",
   "title": "喜好默契二選一：兩人品味大對決",
   "author": "MIMI FACTORY",
   "date": "2026-07-24",
   "color1": "#7aa6ff",
   "color2": "#b78bf5",
   "teaser": "apps/balance-couple-chemistry.html",
   "premium": "apps/balance-couple-chemistry.html",
   "desc": "兩人偷偷選、同時公開，看看你們有多合拍！"
  },
  {
   "id": "burnout-traffic-light",
   "type": "test",
   "title": "倦怠紅綠燈",
   "author": "MIMI FACTORY",
   "date": "2026-07-24",
   "color1": "#7aa6ff",
   "color2": "#b78bf5",
   "teaser": "apps/burnout-traffic-light.html",
   "premium": "apps/burnout-traffic-light.html",
   "desc": "現在你的燈號是什麼顏色？12題自我檢視你的倦怠程度。"
  },
  {
   "id": "how-change-happens",
   "type": "test",
   "title": "變化是如何發生的",
   "author": "MIMI FACTORY",
   "date": "2026-07-24",
   "color1": "#7aa6ff",
   "color2": "#b78bf5",
   "teaser": "apps/how-change-happens.html",
   "premium": "apps/how-change-happens.html",
   "desc": "用多巴胺大師測驗，學會複雜傳染與 25% 引爆點的科學"
  },
  {
   "id": "bimunjeonjaeng",
   "type": "test",
   "title": "碑文戰爭 精通測驗",
   "author": "MIMI FACTORY",
   "date": "2026-07-24",
   "color1": "#7aa6ff",
   "color2": "#b78bf5",
   "teaser": "apps/bimunjeonjaeng.html",
   "premium": "apps/bimunjeonjaeng.html",
   "desc": "廣開土太王陵碑與真鏡大師塔碑——從碑文奪回被抹去的古代史"
  },
  {
   "id": "love-languages",
   "type": "test",
   "title": "愛的語言診斷測驗",
   "author": "MIMI FACTORY",
   "date": "2026-07-24",
   "color1": "#7aa6ff",
   "color2": "#b78bf5",
   "teaser": "apps/love-languages.html",
   "premium": "apps/love-languages.html",
   "desc": "選出你的愛情類型，看看和重要的人有多速配"
  },
  {
   "id": "norwegian-wood",
   "type": "test",
   "title": "挪威的森林 大師測驗",
   "author": "MIMI FACTORY",
   "date": "2026-07-24",
   "color1": "#7aa6ff",
   "color2": "#b78bf5",
   "teaser": "apps/norwegian-wood.html",
   "premium": "apps/norwegian-wood.html",
   "desc": "村上春樹《挪威的森林》— 用30題橫渡失落的故事"
  },
  {
   "id": "thinking-fast-and-slow",
   "type": "test",
   "title": "快思慢想",
   "author": "MIMI FACTORY",
   "date": "2026-07-24",
   "color1": "#7aa6ff",
   "color2": "#b78bf5",
   "teaser": "apps/thinking-fast-and-slow.html",
   "premium": "apps/thinking-fast-and-slow.html",
   "desc": "用多巴胺反覆測驗，學會諾貝爾獎心理學家揭開的心智運作與偏誤"
  },
  {
   "id": "finger-game-friend",
   "type": "test",
   "title": "收指遊戲",
   "author": "MIMI FACTORY",
   "date": "2026-07-24",
   "color1": "#7aa6ff",
   "color2": "#b78bf5",
   "teaser": "apps/finger-game-friend.html",
   "premium": "apps/finger-game-friend.html",
   "desc": "讓兩個人變親近的手指遊戲 — 100 道題目"
  },
  {
   "id": "atomic-habits",
   "type": "test",
   "title": "原子習慣 大師測驗",
   "author": "MIMI FACTORY",
   "date": "2026-07-24",
   "color1": "#7aa6ff",
   "color2": "#b78bf5",
   "teaser": "apps/atomic-habits.html",
   "premium": "apps/atomic-habits.html",
   "desc": "用 30 道測驗掌握每天 1%、複利成長的習慣科學"
  },
  {
   "id": "energy-bus",
   "type": "test",
   "title": "能量巴士 大師測驗",
   "author": "MIMI FACTORY",
   "date": "2026-07-24",
   "color1": "#7aa6ff",
   "color2": "#b78bf5",
   "teaser": "apps/energy-bus.html",
   "premium": "apps/energy-bus.html",
   "desc": "從爆胎的早晨開始，改變人生的 10 條規則 — 30 道測驗與完讀報告。"
  },
  {
   "id": "movie-protagonist",
   "type": "test",
   "title": "電影主角體驗",
   "author": "MIMI FACTORY",
   "date": "2026-07-24",
   "color1": "#7aa6ff",
   "color2": "#b78bf5",
   "teaser": "apps/movie-protagonist.html",
   "premium": "apps/movie-protagonist.html",
   "desc": "兩人並肩坐下，抽出電影名場面即興演出 — 越尷尬默契越高的破冰遊戲"
  },
  {
   "id": "questions-for-two",
   "type": "test",
   "title": "隔壁座位的 100 個問題",
   "author": "MIMI FACTORY",
   "date": "2026-07-24",
   "color1": "#7aa6ff",
   "color2": "#b78bf5",
   "teaser": "apps/questions-for-two.html",
   "premium": "apps/questions-for-two.html",
   "desc": "旅途上一來一往的隨機問題 — 一支手機，兩個人都要回答"
  },
  {
   "id": "sensitivity-meter",
   "type": "test",
   "title": "敏感度儀表",
   "author": "MIMI FACTORY",
   "date": "2026-07-24",
   "color1": "#7aa6ff",
   "color2": "#b78bf5",
   "teaser": "apps/sensitivity-meter.html",
   "premium": "apps/sensitivity-meter.html",
   "desc": "你的感官音量開多大？20 題即時測量感覺 · 共感 · 思考 · 環境。"
  },
  {
   "id": "gohaeng-balance",
   "type": "test",
   "title": "五行平衡測驗",
   "author": "MIMI FACTORY",
   "date": "2026-07-24",
   "color1": "#7aa6ff",
   "color2": "#b78bf5",
   "teaser": "apps/gohaeng-balance.html",
   "premium": "apps/gohaeng-balance.html",
   "desc": "不靠命理，20題測出驅動你的五種能量的平衡。"
  },
  {
   "id": "our-twisted-hero",
   "type": "test",
   "title": "《我們扭曲的英雄》大師測驗",
   "author": "MIMI FACTORY",
   "date": "2026-07-24",
   "color1": "#7aa6ff",
   "color2": "#b78bf5",
   "teaser": "apps/our-twisted-hero.html",
   "premium": "apps/our-twisted-hero.html",
   "desc": "用 30 道題，讀懂教室裡的小小獨裁"
  },
  {
   "id": "the-great-gatsby",
   "type": "test",
   "title": "大亨小傳 多巴胺精通測驗",
   "author": "MIMI FACTORY",
   "date": "2026-07-24",
   "color1": "#7aa6ff",
   "color2": "#b78bf5",
   "teaser": "apps/the-great-gatsby.html",
   "premium": "apps/the-great-gatsby.html",
   "desc": "追著綠光、搆不著的夢 — 用 30 道題記住這部經典"
  },
  {
   "id": "selfish-gene",
   "type": "test",
   "title": "自私的基因 大師測驗",
   "author": "MIMI FACTORY",
   "date": "2026-07-24",
   "color1": "#7aa6ff",
   "color2": "#b78bf5",
   "teaser": "apps/selfish-gene.html",
   "premium": "apps/selfish-gene.html",
   "desc": "用基因的眼光看演化，30 道多巴胺反覆測驗"
  },
  {
   "id": "stranger",
   "type": "test",
   "title": "異鄉人",
   "author": "MIMI FACTORY",
   "date": "2026-07-24",
   "color1": "#7aa6ff",
   "color2": "#b78bf5",
   "teaser": "apps/stranger.html",
   "premium": "apps/stranger.html",
   "desc": "連悲傷都不肯演出的男人的故事 — 用反覆測驗讀懂卡繆《異鄉人》"
  },
  {
   "id": "origin-of-species",
   "type": "test",
   "title": "物種起源大師測驗",
   "author": "MIMI FACTORY",
   "date": "2026-07-24",
   "color1": "#7aa6ff",
   "color2": "#b78bf5",
   "teaser": "apps/origin-of-species.html",
   "premium": "apps/origin-of-species.html",
   "desc": "用多巴胺反覆測驗，掌握達爾文《物種起源》的核心"
  },
  {
   "id": "truth-game",
   "type": "test",
   "title": "真心話遊戲",
   "author": "MIMI FACTORY",
   "date": "2026-07-24",
   "color1": "#7aa6ff",
   "color2": "#b78bf5",
   "teaser": "apps/truth-game.html",
   "premium": "apps/truth-game.html",
   "desc": "並肩坐著抽卡、輪流說真心話的雙人遊戲"
  },
  {
   "id": "real-zodiac",
   "type": "test",
   "title": "真正的星座測驗",
   "author": "MIMI FACTORY",
   "date": "2026-07-24",
   "color1": "#7aa6ff",
   "color2": "#b78bf5",
   "teaser": "apps/real-zodiac.html",
   "premium": "apps/real-zodiac.html",
   "desc": "不是生日，而是性格所指向的靈魂星座 — 12題揭曉"
  },
  {
   "id": "tarot",
   "type": "test",
   "title": "塔羅心理卡",
   "author": "MIMI FACTORY",
   "date": "2026-07-24",
   "color1": "#7aa6ff",
   "color2": "#b78bf5",
   "teaser": "apps/tarot.html",
   "premium": "apps/tarot.html",
   "desc": "抽的不是命運，是問題 — 22張象徵變成心理學的鏡子"
  },
  {
   "id": "toji",
   "type": "test",
   "title": "《土地》多巴胺大師測驗",
   "author": "MIMI FACTORY",
   "date": "2026-07-24",
   "color1": "#7aa6ff",
   "color2": "#b78bf5",
   "teaser": "apps/toji.html",
   "premium": "apps/toji.html",
   "desc": "崔參判家與平沙里的人們 — 半世紀大河史詩，30 題掌握"
  },
  {
   "id": "stats-and-me",
   "type": "test",
   "title": "統計與我",
   "author": "MIMI FACTORY",
   "date": "2026-07-24",
   "color1": "#7aa6ff",
   "color2": "#b78bf5",
   "teaser": "apps/stats-and-me.html",
   "premium": "apps/stats-and-me.html",
   "desc": "選下去就公開真實統計 — 你是主流，還是稀有物種？"
  },
  {
   "id": "pensees",
   "type": "test",
   "title": "思想錄 大師測驗",
   "author": "MIMI FACTORY",
   "date": "2026-07-24",
   "color1": "#7aa6ff",
   "color2": "#b78bf5",
   "teaser": "apps/pensees.html",
   "premium": "apps/pensees.html",
   "desc": "用多巴胺記住《思想錄》核心的反覆大師測驗"
  },
  {
   "id": "personal-color",
   "type": "test",
   "title": "個人色彩自我診斷",
   "author": "MIMI FACTORY",
   "date": "2026-07-24",
   "color1": "#7aa6ff",
   "color2": "#b78bf5",
   "teaser": "apps/personal-color.html",
   "premium": "apps/personal-color.html",
   "desc": "照一次鏡子、12 題，找出最適合你的季節色彩。"
  }
 ],
 "updated": "2026-07-24"
}